[{"Id":1,"UserId":1,"ProductId":11,"ProductName":"Fossil Analog Rose Gold","Quantity":5,"Price":12885.0},{"Id":2,"UserId":1,"ProductId":17,"ProductName":"Fossil Analog Rose Gold","Quantity":3,"Price":24213.0},{"Id":3,"UserId":1,"ProductId":23,"ProductName":"Moroccanoil Curl Spray","Quantity":1,"Price":1512.0},{"Id":4,"UserId":1,"ProductId":24,"ProductName":"Moroccanoil Body Fragrance","Quantity":1,"Price":1080.0},{"Id":5,"UserId":1,"ProductId":21,"ProductName":"Moroccanoil Cleansing Bar","Quantity":1,"Price":585.0},{"Id":6,"UserId":1,"ProductId":8,"ProductName":"MDN Kids Vinyl","Quantity":1,"Price":1099.0},{"Id":7,"UserId":1,"ProductId":4,"ProductName":"Supples Baby Diaper Pants","Quantity":2,"Price":700.0},{"Id":8,"UserId":1,"ProductId":1,"ProductName":"Supples Baby Pants Diapers","Quantity":1,"Price":575.0},{"Id":9,"UserId":1,"ProductId":10,"ProductName":"Mee Mee Baby Walker","Quantity":1,"Price":2399.0},{"Id":10,"UserId":1,"ProductId":3,"ProductName":"Supples Baby Wet Wipes","Quantity":1,"Price":369.0},{"Id":11,"UserId":1,"ProductId":9,"ProductName":"Mother Sparsh Tummy Roll On for Baby","Quantity":1,"Price":194.0},{"Id":12,"UserId":1,"ProductId":20,"ProductName":"Moroccanoil Color","Quantity":1,"Price":1512.0},{"Id":13,"UserId":1,"ProductId":25,"ProductName":"Moroccanoil Body Collection Original Kit","Quantity":1,"Price":3735.0},{"Id":14,"UserId":1,"ProductId":18,"ProductName":"Fossil Riley Analog Rose Gold","Quantity":1,"Price":9995.0},{"Id":15,"UserId":1,"ProductId":23,"ProductName":"Moroccanoil Curl Spray","Quantity":1,"Price":1512.0},{"Id":16,"UserId":1,"ProductId":17,"ProductName":"Fossil Analog Rose Gold","Quantity":1,"Price":8071.0},{"Id":17,"UserId":1,"ProductId":11,"ProductName":"Fossil Analog Rose Gold","Quantity":1,"Price":2577.0},{"Id":18,"UserId":1,"ProductId":6,"ProductName":"Johnson's Baby Top to Toe","Quantity":1,"Price":288.0},{"Id":19,"UserId":1,"ProductId":22,"ProductName":"Moroccanoil Body Cleansing","Quantity":1,"Price":585.0},{"Id":20,"UserId":1,"ProductId":16,"ProductName":"Fossil Georgia Analog Silver Dial","Quantity":1,"Price":4540.0},{"Id":21,"UserId":1,"ProductId":19,"ProductName":"Moroccanoil Blow Dry","Quantity":1,"Price":1512.0},{"Id":22,"UserId":1,"ProductId":12,"ProductName":"Fossil Sport Smartwatch","Quantity":1,"Price":11995.0},{"Id":23,"UserId":1,"ProductId":26,"ProductName":"The 5 AM Club","Quantity":2,"Price":398.0}]